langchain_openai_like/__init__.py
langchain_openai_like/py.typed
langchain_openai_like/chat_model/__init__.py
langchain_openai_like/chat_model/adapters.py
langchain_openai_like/chat_model/base.py
langchain_openai_like/chat_model/providers/__init__.py
langchain_openai_like/chat_model/providers/base_model.py
langchain_openai_like/chat_model/providers/chat_models.py
langchain_openai_like/chat_model/providers/custom.py
langchain_openai_like/chat_model/providers/dashscope.py
langchain_openai_like/chat_model/providers/deepseek.py
langchain_openai_like/chat_model/providers/groq.py
langchain_openai_like/chat_model/providers/huggingface.py
langchain_openai_like/chat_model/providers/moonshot.py
langchain_openai_like/chat_model/providers/ollama.py
langchain_openai_like/chat_model/providers/openrouter.py
langchain_openai_like/chat_model/providers/siliconflow.py
langchain_openai_like/chat_model/providers/vllm.py
langchain_openai_like/chat_model/providers/zai.py
langchain_openai_like/embbeding/__init__.py
langchain_openai_like/embbeding/base.py
langchain_openai_like-0.1.1.dist-info/METADATA
langchain_openai_like-0.1.1.dist-info/WHEEL
langchain_openai_like-0.1.1.dist-info/licenses/LICENSE
langchain_openai_like-0.1.1.dist-info/RECORD
