Metadata-Version: 2.4
Name: langchain-openai-like
Version: 0.1.1
Summary: A utils to connect to all models compatible with the OpenAI style
Project-URL: Source Code, https://github.com/TBice123123/langchain-openai-like
Author-email: tiebingice <tiebingice123@outlook.com>
License-File: LICENSE
Requires-Python: >=3.11
Requires-Dist: langchain-openai>=0.3.32
Requires-Dist: langchain>=0.3.27
Requires-Dist: python-dotenv>=1.1.1
